Metadata-Version: 1.0
Name: translate-hub
Version: 0.0.1
Summary: Translate Hub
Home-page: UNKNOWN
Author: UNKNOWN
Author-email: UNKNOWN
License: UNKNOWN
Platform: UNKNOWN
